mqtt_viewer/App.py
mqtt_viewer/ConnectionPage.py
mqtt_viewer/MqttHandler.py
mqtt_viewer/SignalManager.py
mqtt_viewer/TopicLog.py
mqtt_viewer/TopicsList.py
mqtt_viewer/ViewerPage.py
mqtt_viewer/__init__.py
mqtt_viewer/main_gui.py
mqtt_viewer/py.typed
mqtt_viewer/utils.py
ki2_mqtt_viewer-1.0.1.dist-info/LICENSE
ki2_mqtt_viewer-1.0.1.dist-info/METADATA
ki2_mqtt_viewer-1.0.1.dist-info/WHEEL
ki2_mqtt_viewer-1.0.1.dist-info/entry_points.txt
ki2_mqtt_viewer-1.0.1.dist-info/RECORD
