Metadata-Version: 2.1
Name: ki2-mqtt-viewer
Version: 1.0.1
Summary: MQTT Viewer is a user-friendly application designed to help users interact with MQTT brokers effortlessly. With an intuitive interface, it allows users to connect to an MQTT server, view and log messages for different topics, and publish messages with ease.
License: MIT
Author: Adrien KERFOURN
Author-email: ak.sitecontact@gmail.com
Requires-Python: >=3.10,<3.14
Classifier: License :: OSI Approved :: MIT License
Classifier: Programming Language :: Python :: 3
Classifier: Programming Language :: Python :: 3.10
Classifier: Programming Language :: Python :: 3.11
Classifier: Programming Language :: Python :: 3.12
Classifier: Programming Language :: Python :: 3.13
Requires-Dist: ki2-python-utils (>=0.3.5,<0.4.0)
Requires-Dist: paho-mqtt (>=2.1.0,<3.0.0)
Requires-Dist: platformdirs (>=4.3.6,<5.0.0)
Requires-Dist: pyside6 (==6.8.1) ; sys_platform == "linux"
Requires-Dist: pyside6 (==6.8.1) ; sys_platform == "win32"
Requires-Dist: pyside6 (>=6.8.1.1,<7.0.0.0) ; sys_platform == "macos"
Requires-Dist: typing-extensions (>=4.12.2,<5.0.0)
